[
    {
        "command": "speed 100",
        "result": "OK"
    },
    {
        "command": "forward 50",
        "result": "OK"
    },
    {
        "command": "cw 90",
        "result": "OK"
    },
    {
        "command": "forward 50",
        "result": "OK"
    },
    {
        "command": "cw 90",
        "result": "OK"
    },
    {
        "command": "forward 50",
        "result": "OK"
    },
    {
        "command": "cw 90",
        "result": "OK"
    },
    {
        "command": "forward 50",
        "result": "OK"
    },
    {
        "command": "cw 90",
        "result": "OK"
    },
    {
        "command": "back 50",
        "result": "OK"
    },
    {
        "command": "ccw 90",
        "result": "OK"
    },
    {
        "command": "back 50",
        "result": "OK"
    },
    {
        "command": "ccw 90",
        "result": "OK"
    },
    {
        "command": "back 50",
        "result": "OK"
    },
    {
        "command": "ccw 90",
        "result": "OK"
    }
]
